simplebeep/__init__.py
simplebeep/functions.py
simplebeep-0.0.2.dist-info/LICENSE
simplebeep-0.0.2.dist-info/METADATA
simplebeep-0.0.2.dist-info/WHEEL
simplebeep-0.0.2.dist-info/top_level.txt
simplebeep-0.0.2.dist-info/RECORD
